Workbook

Sheet Registro 2026
A1: PEÑA TAURINA PEGUERINOS
A2: Ávila, Castilla y León · Libro de Ingresos y Gastos
A3: Ejercicio 2026
A5: FECHA | B5: CONCEPTO | C5: CATEGORÍA / NOTAS | D5: INGRESO (€) | E5: GASTO (€)
A6: 46093 | B6: cuota semestral socios | D6: 800
A7: 46100 | B7: suscripcion canal tv y cesion de local | C7: colaboracion socio
A8: 46106 | B8: reunion cena de convivencia | C8: 🧾 Ver Ticket Cena | E8: 150
A9: 46134 | B9: dotacion camisetas y pañoletas | C9: colaboracion socio
A10: 46138 | B10: compras cena inaugural | C10: 🧾 Ver Ticket Compras (2) | E10: 130
A11: 46139 | B11: tarjetas boligrafos | C11: colaboracion socio
A12: 46158 | B12: Venta Loteria | D12: 27.5
A13: 46164 | B13: Material papelería | C13: Material · 🧾 Ver Ticket Papelería | E13: 30
A14: 46172 | B14: Venta Lotería | D14: 57
A15: 46182 | B15: Venta Lotería | D15: 23.5
A16: 46188 | B16: compra de entradas | C16: 🧾 Ver Factura Entradas | E16: 308
A17: 46191 | B17: Venta Lotería | D17: 30
A18: 46197 | B18: Venta Lotería | D18: 30
A19: 46197 | B19: Devolución entrada | D19: 40
A20: 46207 | B20: Venta Lotería | D20: 52
A21: 46218 | B21: Venta Lotería | D21: 20.5
A22: 46222 | B22: Venta Lotería | D22: 34
A23: 46244 | B23: Venta Lotería | D23: 83
A24: 46249 | B24: Pago toro de fuego | E24: 100
A25: 46256 | B25: Venta Lotería | D25: 34
A26: 46263 | B26: Venta Lotería | D26: 34
A27: 46270 | B27: Venta Lotería | D27: 29
A28: 46277 | B28: Cuota semestral socios (septiembre) | C28: 13 de 16 socios | D28: 650
A29: 46291 | B29: Cuota semestral socios (septiembre) | C29: José Carlos García Pozo | D29: 50
A30: 46291 | B30: Cuota semestral socios (septiembre) | C30: José Antonio Gálvez | D30: 50
A31: 📊 TOTAL PARCIAL | D31: =SUM(D6:D30) -> 2044.5 | E31: =SUM(E6:E30) -> 718 | F31: =D31-E31 -> 1326.5
A33: TOTALES | D33: =SUM(D6:D30) -> 2044.5 | E33: =SUM(E6:E30) -> 718 | F33: =D33-E33 -> 1326.5
A34: SALDO (Ingresos - Gastos) | F34: =D33-E33 -> 1326.5
A35: 📥 Total Ingresos | D35: =D33 -> 2044.5 | E35: =E33 -> 718
A36: 📤 Total Gastos | E36: =E31 -> 718

Sheet Resumen Anual
A1: PEÑA TAURINA PEGUERINOS — RESUMEN ANUAL
A2: Ejercicio 2026
A4: CATEGORÍA | B4: INGRESOS (€) | C4: GASTOS (€) | D4: SALDO (€)
A5: Cuotas socios | B5: =SUMIF('Registro 2026'!B6:B30,"Cuota*",'Registro 2026'!D6:D30) -> 1550 | C5: 0 | D5: =B5-C5 -> 1550
A6: Lotería | B6: =SUMIF('Registro 2026'!B6:B30,"Venta Loter?a",'Registro 2026'!D6:D30) -> 454.5 | C6: 0 | D6: =B6-C6 -> 454.5
A7: Cenas y convivencias | B7: 0 | C7: ='Registro 2026'!E8+'Registro 2026'!E10 -> 280 | D7: =B7-C7 -> -280
A8: Material papelería | B8: 0 | C8: =SUMIF('Registro 2026'!B6:B30,"Material*",'Registro 2026'!E6:E30) -> 30 | D8: =B8-C8 -> -30
A9: Entradas corrida (y devolución) | B9: =SUMIF('Registro 2026'!B6:B30,"Devoluci?n entrada",'Registro 2026'!D6:D30) -> 40 | C9: =SUMIF('Registro 2026'!B6:B30,"compra de entradas",'Registro 2026'!E6:E30) -> 308 | D9: =B9-C9 -> -268
A10: Toro de fuego | B10: 0 | C10: =SUMIF('Registro 2026'!B6:B30,"Pago toro de fuego",'Registro 2026'!E6:E30) -> 100 | D10: =B10-C10 -> -100
A11: Otros | B11: 0 | C11: 0 | D11: =B11-C11 -> 0
A12: TOTAL | B12: =SUM(B5:B11) -> 2044.5 | C12: =SUM(C5:C11) -> 718 | D12: =B12-C12 -> 1326.5

Sheet Socios y Cuotas
A1: PEÑA TAURINA PEGUERINOS — CONTROL DE CUOTAS
A2: Cuota anual: 100 € en dos plazos de 50 € (marzo y septiembre)
A4: Nº | B4: NOMBRE Y APELLIDOS | C4: 1.er PLAZO Marzo | D4: PAGADO Marzo | E4: 2.º PLAZO Septiembre | F4: PAGADO Sept. | G4: ESTADO
A5: 1 | B5: Miguel Ángel Rodríguez Fariña | C5: 50 | D5: Sí | E5: 50 | F5: Sí | G5: =IF(AND(D5="Sí",F5="Sí"),"Al día","Pendiente") -> Al día
A6: 2
A7: 3 | B7: Daniel Álvarez García | C7: 50 | D7: Sí | E7: 50 | F7: Sí | G7: =IF(AND(D7="Sí",F7="Sí"),"Al día","Pendiente") -> Al día
A8: 4 | B8: Joaquín Rodríguez Fariña | C8: 50 | D8: Sí | E8: 50 | F8: Sí | G8: =IF(AND(D8="Sí",F8="Sí"),"Al día","Pendiente") -> Al día
A9: 5 | B9: Juan Fernando Casado Tormo | C9: 50 | D9: Sí | E9: 50 | F9: Sí | G9: =IF(AND(D9="Sí",F9="Sí"),"Al día","Pendiente") -> Al día
A10: 6 | B10: Félix Rodríguez | C10: 50 | D10: Sí | E10: 50 | F10: Sí | G10: =IF(AND(D10="Sí",F10="Sí"),"Al día","Pendiente") -> Al día
A11: 7 | B11: José Carlos García Pozo | C11: 50 | D11: Sí | E11: 50 | F11: Sí | G11: =IF(AND(D11="Sí",F11="Sí"),"Al día","Pendiente") -> Al día
A12: 8 | B12: Jaime Vila-Coro Laviña | C12: 50 | D12: Sí | E12: 50 | F12: Sí | G12: =IF(AND(D12="Sí",F12="Sí"),"Al día","Pendiente") -> Al día
A13: 9 | B13: José Luis Cañaveral-Fernández | C13: 50 | D13: Sí | E13: 50 | F13: Sí | G13: =IF(AND(D13="Sí",F13="Sí"),"Al día","Pendiente") -> Al día
A14: 10 | B14: Alejandro Tanarro García | C14: 50 | D14: Sí | E14: 50 | F14: Sí | G14: =IF(AND(D14="Sí",F14="Sí"),"Al día","Pendiente") -> Al día
A15: 11 | B15: Luis Alfonso García | C15: 50 | D15: Sí | E15: 50 | F15: Sí | G15: =IF(AND(D15="Sí",F15="Sí"),"Al día","Pendiente") -> Al día
A16: 12 | B16: José Miguel Cañaveral-Fernández Santos | C16: 50 | D16: Sí | E16: 50 | F16: Sí | G16: =IF(AND(D16="Sí",F16="Sí"),"Al día","Pendiente") -> Al día
A17: 13 | B17: Alfonso Rilo | C17: 50 | D17: Sí | E17: 50 | F17: Sí | G17: =IF(AND(D17="Sí",F17="Sí"),"Al día","Pendiente") -> Al día
A18: 14 | B18: Sergio Monge Gómez | C18: 50 | D18: Sí | E18: 50 | F18: Sí | G18: =IF(AND(D18="Sí",F18="Sí"),"Al día","Pendiente") -> Al día
... A21: 17 | B21: Antonio Rosado | C21: 50 | D21: Sí | E21: 50 | F21: No | G21: =IF(AND(D21="Sí",F21="Sí"),"Al día","Pendiente") -> Pendiente
A26: TOTAL RECAUDADO | C26: =SUMIF(D5:D25,"Sí",C5:C25) -> 800 | E26: =SUMIF(F5:F25,"Sí",E5:E25) -> 750
A28: SOCIOS SIMPATIZANTES
A29: Aportación voluntaria de apoyo a la Peña, cuota distinta a la de socio de número
A31: Nº | B31: NOMBRE Y APELLIDOS | C31: CUOTA ANUAL (€) | D31: PAGADO | E31: FECHA PAGO | F31: NOTAS
A32: 1 | B32: Carlos Herranz | C32: 40 | D32: No
A34: TOTAL RECAUDADO | C34: =SUMIF(D32:D32,"Sí",C32:C32) -> 0

Sheet Ticket Cena
A1: 📷 Ticket Cena — Mesón El Risco del Águila (25/03/2026)
A2: Importe: 147,43 €

Sheet Tickets Compra
A1: 📷 Tickets Compra — Carnicería Las Navas + Lupa (25/04/2026)
A2: Carnicería: 58,03 € | Lupa: 66,08 € | Total: 124,11 €

Sheet Ticket Papelería
A1: 📷 Ticket Papelería — Global Soluciones Gráficas SL (22/05/2026)
A2: Importe: 30,00 € | Base imp.: 24,79 € | IVA (21%): 5,21 € | Factura: FT 0002/064504

Sheet Factura Entradas
A1: FACTURA - ENTRADA CORRIDA DE TOROS
A3: Fecha: | B3: 15/06/2026
A4: Email: | B4: garcia1701@gmail.com
A5: Localizador: | B5: GP020030
A7: EVENTO
A8: Tipo: Corrida de Toros
A9: Fecha: Sábado, 20 de junio de 2026, 19:00h
A10: Lugar: Plaza de Toros de Ávila
A11: Dirección: Carretera Burgohondo, 13
A13: ENTRADAS
A14: Cantidad: 8 entradas
A15: Tendido: Tendido 9, Fila 12
A16: Asientos: 16, 17, 18, 19, 20, 21, 22, 23
A17: Tarifa: GENERAL - 35,00€ c/u
A19: RESUMEN ECONÓMICO
A20: Precio base (8 x 35€): | B20: 280
A21: Gastos de gestión: | B21: 28
A22: TOTAL: | B22: 308
A24: Número de Pedido: 2306n45A91UW
A25: Autorización: 355901
A26: Comercio: 347434433-001
